uk_address_matcher/__init__.py
uk_address_matcher/cleaning/chunking_strategies.py
uk_address_matcher/cleaning/pipelines.py
uk_address_matcher/cleaning/steps/__init__.py
uk_address_matcher/cleaning/steps/normalisation.py
uk_address_matcher/cleaning/steps/regexes.py
uk_address_matcher/cleaning/steps/term_frequencies.py
uk_address_matcher/cleaning/steps/token_parsing.py
uk_address_matcher/cleaning/steps/tokenisation.py
uk_address_matcher/data/address_abbreviations.json
uk_address_matcher/data/address_token_frequencies.parquet
uk_address_matcher/data/common_end_tokens.csv
uk_address_matcher/data/common_uk_end_tokens.json
uk_address_matcher/data/non_traditional_address_types.json
uk_address_matcher/data/numeric_token_frequencies.parquet
uk_address_matcher/data/splink_model.json
uk_address_matcher/linking_model/blocking.py
uk_address_matcher/linking_model/splink_model.py
uk_address_matcher/linking_model/training.py
uk_address_matcher/linking_model/exact_matching/__init__.py
uk_address_matcher/linking_model/exact_matching/annotate_exact_matches.py
uk_address_matcher/linking_model/exact_matching/input_filters.py
uk_address_matcher/linking_model/exact_matching/matching_stages.py
uk_address_matcher/linking_model/exact_matching/peeled_address_matching.py
uk_address_matcher/linking_model/exact_matching/resolve_with_trigrams.py
uk_address_matcher/post_linkage/accuracy_from_labels.py
uk_address_matcher/post_linkage/analyse_results.py
uk_address_matcher/post_linkage/identify_distinguishing_tokens.py
uk_address_matcher/post_linkage/match_candidate_selection.py
uk_address_matcher/sql_pipeline/helpers.py
uk_address_matcher/sql_pipeline/match_reasons.py
uk_address_matcher/sql_pipeline/runner.py
uk_address_matcher/sql_pipeline/steps.py
uk_address_matcher/sql_pipeline/validation.py
uk_address_matcher-0.0.4.dist-info/METADATA
uk_address_matcher-0.0.4.dist-info/WHEEL
uk_address_matcher-0.0.4.dist-info/top_level.txt
uk_address_matcher-0.0.4.dist-info/RECORD
