Metadata-Version: 2.4
Name: uk_address_matcher
Version: 0.0.4
Summary: A package for matching UK addresses using a pretrained Splink model
Author-email: Robin Linacre <robinlinacre@hotmail.com>
License: MIT
Project-URL: Repository, https://github.com/robinL/uk_address_matcher
Requires-Python: >=3.9
Requires-Dist: duckdb>=1.4.1
Requires-Dist: splink==4.0.8
Requires-Dist: sqlglot==26.6.0
Provides-Extra: dev
Requires-Dist: ipykernel>=6.29.4; extra == "dev"
Requires-Dist: boto3>=1.40.0; extra == "dev"
